anonpi/__init__.py
anonpi/error.py
anonpi/resources.py
anonpi/enums/__init__.py
anonpi/enums/languages.py
anonpi/models/__init__.py
anonpi/models/main/__init__.py
anonpi/models/main/call.py
anonpi/models/main/recording.py
anonpi/models/main/user.py
anonpi/models/manager/__init__.py
anonpi/models/manager/converter.py
anonpi/models/manager/meta.py
anonpi/models/manager/requester.py
anonpi/models/nested/__init__.py
anonpi/models/nested/nest_converter.py
anonpi/models/nested/nested_initiator_check.py
anonpi/models/nested/nested_resource.py
anonpi/models/nested/super_record.py
anonpi/models/sub/__init__.py
anonpi/models/sub/anonobject.py
anonpi/models/sub/callconn.py
anonpi/models/sub/callobject.py
anonpi/models/sub/userconn.py
anonpi/models/sub/records/__init__.py
anonpi/models/sub/records/sub/__init__.py
anonpi/models/sub/records/sub/group.py
anonpi/models/sub/records/sub/record.py
anonpi/models/sub/records/super/__init__.py
anonpi/models/sub/records/super/record_expand.py
anonpi/models/sub/records/super/record_single.py
anonpi-2.0.1.dist-info/LICENSE
anonpi-2.0.1.dist-info/METADATA
anonpi-2.0.1.dist-info/WHEEL
anonpi-2.0.1.dist-info/top_level.txt
anonpi-2.0.1.dist-info/RECORD
