Metadata-Version: 2.1
Name: anonpi
Version: 2.0.1
Summary: The "anonpi" module is a Python package designed to streamline interactions with calling systems. It simplifies the development of applications that require features like machine detection, IVR, DTMF handling, call recording, playback, and more. This module provides a clean and intuitive API for seamless integration into Python applications.
Author: EvenueStar
License: MIT
Keywords: anonpi,python,calling,systems,api,wrapper,module
Classifier: Development Status :: 5 - Production/Stable
Classifier: Intended Audience :: Developers
Classifier: Topic :: Communications :: Telephony
Classifier: License :: OSI Approved :: MIT License
Classifier: Programming Language :: Python :: 3.9
Requires-Python: >=3.9
License-File: LICENSE
